comic_html_view_generator/__init__.py
comic_html_view_generator/chvg.py
comic_html_view_generator/simulated_comic_volume_001.cbz
comic_html_view_generator/test_chvg.py
comic_html_view_generator/test_output_volume/simulated_comic_volume_001/issue001/img001.png
comic_html_view_generator/test_output_volume/simulated_comic_volume_001/issue001/img002.png
comic_html_view_generator/test_output_volume/simulated_comic_volume_001/issue002/img001.png
comic_html_view_generator/test_output_volume/simulated_comic_volume_001/issue002/img002.png
comic_html_view_generator-0.2.3.dist-info/entry_points.txt
comic_html_view_generator-0.2.3.dist-info/LICENSE
comic_html_view_generator-0.2.3.dist-info/WHEEL
comic_html_view_generator-0.2.3.dist-info/METADATA
comic_html_view_generator-0.2.3.dist-info/RECORD
