Metadata-Version: 2.1
Name: comic-html-view-generator
Version: 0.2.3
Summary: HTML generator to view comic books
Author: Leland Batey
Author-email: lelandbatey@gmail.com
Requires-Python: >=3.8,<4.0
Classifier: Programming Language :: Python :: 3
Classifier: Programming Language :: Python :: 3.8
Classifier: Programming Language :: Python :: 3.9
